bioage/__init__.py
bioage-0.1.1.dist-info/METADATA
bioage-0.1.1.dist-info/WHEEL
bioage-0.1.1.dist-info/RECORD
